inductance/__init__.py
inductance/_numba.py
inductance/coils.py
inductance/elliptics.py
inductance/filaments.py
inductance/mutual.py
inductance/self.py
inductance/utils.py
inductance-0.1.7.dist-info/METADATA
inductance-0.1.7.dist-info/WHEEL
inductance-0.1.7.dist-info/licenses/LICENSE
inductance-0.1.7.dist-info/RECORD
