Metadata-Version: 2.4
Name: inductance
Version: 0.1.7
Summary: Code for 2D inductance calculations
Project-URL: Homepage, https://github.com/dgarnier/inductance
Project-URL: Repository, https://github.com/dgarnier/inductance
Project-URL: Documentation, https://inductance.readthedocs.io
Project-URL: Changelog, https://github.com/dgarnier/inductance/releases
Author-email: Darren Garnier <dgarnier@reinrag.net>
License: MIT License
License-File: LICENSE
Keywords: electromagnetism,inductance,physics
Classifier: Development Status :: 4 - Beta
Classifier: Intended Audience :: Developers
Classifier: Intended Audience :: Science/Research
Classifier: License :: OSI Approved :: MIT License
Classifier: Natural Language :: English
Classifier: Programming Language :: Python :: 3.10
Classifier: Programming Language :: Python :: 3.11
Classifier: Programming Language :: Python :: 3.12
Classifier: Programming Language :: Python :: 3.13
Requires-Python: <3.14,>=3.10
Requires-Dist: click>=8.2.1
Requires-Dist: docutils>=0.21.2
Requires-Dist: numba>=0.61.2
Requires-Dist: numpy<2.3,>=1.24
Requires-Dist: pre-commit>=3.8.0
